CHANGES.md
MANIFEST.in
README.md
setup.cfg
setup.py
pyramid_vgid_oauth2/__init__.py
pyramid_vgid_oauth2/events.py
pyramid_vgid_oauth2/models.py
pyramid_vgid_oauth2/views.py
pyramid_vgid_oauth2.egg-info/PKG-INFO
pyramid_vgid_oauth2.egg-info/SOURCES.txt
pyramid_vgid_oauth2.egg-info/dependency_links.txt
pyramid_vgid_oauth2.egg-info/not-zip-safe
pyramid_vgid_oauth2.egg-info/requires.txt
pyramid_vgid_oauth2.egg-info/top_level.txt