Metadata-Version: 1.1
Name: pyramid-vgid-oauth2
Version: 1.0.2
Summary: pyramid_vgid_oauth2
Home-page: http://gitlab.vnpid.com/vgid/pyramid_vgid_oauth2
Author: Tarzan
Author-email: hoc3010@gmail.com
License: UNKNOWN
Keywords: web wsgi bfg pylons pyramid
Platform: UNKNOWN
Classifier: Programming Language :: Python
Classifier: Framework :: Pyramid
Classifier: Topic :: Internet :: WWW/HTTP
Classifier: Topic :: Internet :: WWW/HTTP :: WSGI :: Application
